purecpp/RagPUREAI.cpython-312-x86_64-linux-gnu.so
purecpp/__init__.py
purecpp-0.0.22.dist-info/METADATA
purecpp-0.0.22.dist-info/WHEEL
purecpp-0.0.22.dist-info/top_level.txt
purecpp-0.0.22.dist-info/RECORD
